flask_media
test
