Metadata-Version: 1.1
Name: flask-media
Version: 0.4.4
Summary: Flask extestion helper uploads files
Home-page: http://bitbucket.org/cent/flask-media/
Author: Vadim Statishin
Author-email: statishin@gmail.com
License: BSD License
Keywords: flask file upload image
Platform: any
Classifier: Development Status :: 4 - Beta
Classifier: Environment :: Web Environment
Classifier: Intended Audience :: Developers
Classifier: License :: OSI Approved :: BSD License
Classifier: Operating System :: OS Independent
Classifier: Programming Language :: Python
Classifier: Topic :: Internet :: WWW/HTTP :: Dynamic Content
Classifier: Topic :: Database
Classifier: Topic :: Software Development :: Libraries :: Python Modules
Requires: Flask
Requires: sqlalchemy
Requires: Pillow
